sage_invoice/__init__.py
sage_invoice/admin/__init__.py
sage_invoice/admin/actions/__init__.py
sage_invoice/admin/actions/download_pdf.py
sage_invoice/admin/category.py
sage_invoice/admin/invoice.py
sage_invoice/api/helpers/versioning.py
sage_invoice/api/mixins/__init__.py
sage_invoice/api/mixins/exception.py
sage_invoice/api/serializers/__init__.py
sage_invoice/api/serializers/category.py
sage_invoice/api/serializers/column.py
sage_invoice/api/serializers/expense.py
sage_invoice/api/serializers/invoice.py
sage_invoice/api/serializers/item.py
sage_invoice/api/urls.py
sage_invoice/api/views/__init__.py
sage_invoice/api/views/category.py
sage_invoice/api/views/column.py
sage_invoice/api/views/expense.py
sage_invoice/api/views/invoice.py
sage_invoice/api/views/item.py
sage_invoice/apps.py
sage_invoice/check.py
sage_invoice/helpers/__init__.py
sage_invoice/helpers/choice.py
sage_invoice/helpers/funcs.py
sage_invoice/locale/ar/LC_MESSAGES/django.po
sage_invoice/locale/en/LC_MESSAGES/django.po
sage_invoice/locale/fa/LC_MESSAGES/django.po
sage_invoice/migrations/0001_initial.py
sage_invoice/migrations/0002_alter_invoice_template_choice.py
sage_invoice/migrations/0003_alter_expense_invoice_alter_invoice_category_and_more.py
sage_invoice/migrations/__init__.py
sage_invoice/models/__init__.py
sage_invoice/models/category.py
sage_invoice/models/column.py
sage_invoice/models/expense.py
sage_invoice/models/invoice.py
sage_invoice/models/item.py
sage_invoice/resource.py
sage_invoice/service/__init__.py
sage_invoice/service/discovery.py
sage_invoice/service/invoice_create.py
sage_invoice/service/total.py
sage_invoice/signals.py
sage_invoice/static/assets/css/style.css
sage_invoice/static/assets/img/arrow_bg.svg
sage_invoice/static/assets/img/coffy_shop_img.svg
sage_invoice/static/assets/img/header_bg.jpg
sage_invoice/static/assets/img/header_bg_2.jpg
sage_invoice/static/assets/img/logo.svg
sage_invoice/static/assets/img/logo_accent.svg
django_sage_invoice-0.1.6.dist-info/LICENSE
django_sage_invoice-0.1.6.dist-info/METADATA
django_sage_invoice-0.1.6.dist-info/WHEEL
django_sage_invoice-0.1.6.dist-info/RECORD
