Metadata-Version: 2.1
Name: django-sage-invoice
Version: 0.1.6
Summary: A project for invoice generation and NFC integration.
Home-page: https://github.com/sageteamorg/django-sage-invoice
License: MIT
Keywords: django,invoice,sageteam,django-packages
Author: Radin Ghahremani
Author-email: radin@sageteam.org
Requires-Python: >=3.9,<4.0
Classifier: Development Status :: 3 - Alpha
Classifier: Framework :: Django
Classifier: License :: OSI Approved :: MIT License
Classifier: Programming Language :: Python :: 3
Classifier: Programming Language :: Python :: 3.9
Classifier: Programming Language :: Python :: 3.10
Classifier: Programming Language :: Python :: 3.11
Classifier: Programming Language :: Python :: 3.12
Requires-Dist: bandit[toml] (>=1.7.9,<2.0.0)
Requires-Dist: django (>=4.2,<5.0) ; python_version >= "3.8" and python_version < "3.10"
Requires-Dist: django (>=4.2,<5.3) ; python_version >= "3.10"
Requires-Dist: django-import-export (>=4.1.1,<5.0.0)
Requires-Dist: django-jsonform (>=2.22.0,<3.0.0)
Requires-Dist: django-sage-tools (>=0.3.5,<0.4.0)
Requires-Dist: djangorestframework (>=3.15.2,<4.0.0)
Requires-Dist: jinja2 (>=3.1.4,<4.0.0)
Requires-Dist: pillow (>=10.4.0,<11.0.0)
Project-URL: Documentation, https://django-sage-invoice.readthedocs.io/en/latest/
Project-URL: Issues, https://github.com/sageteamorg/django-sage-invoice/issues
Project-URL: Repository, https://github.com/sageteamorg/django-sage-invoice
Project-URL: Source Code, https://github.com/sageteamorg/django-sage-invoice
